mindsight_full_api/__init__.py
mindsight_full_api/helpers/__init__.py
mindsight_full_api/helpers/base_requests.py
mindsight_full_api/helpers/exceptions.py
mindsight_full_api/helpers/models.py
mindsight_full_api/scripts/__init__.py
mindsight_full_api/scripts/absences.py
mindsight_full_api/scripts/access_rules.py
mindsight_full_api/scripts/assessments.py
mindsight_full_api/scripts/bonus.py
mindsight_full_api/scripts/cost_center.py
mindsight_full_api/scripts/extra_hours.py
mindsight_full_api/scripts/people.py
mindsight_full_api/scripts/performance_evaluation_round.py
mindsight_full_api/scripts/performance_evaluations.py
mindsight_full_api/scripts/performance_indicators.py
mindsight_full_api/scripts/performance_labels.py
mindsight_full_api/scripts/performance_missions.py
mindsight_full_api/scripts/performance_sections.py
mindsight_full_api/scripts/positions.py
mindsight_full_api/scripts/raise_type.py
mindsight_full_api/scripts/salaries.py
mindsight_full_api/scripts/shares.py
mindsight_full_api/scripts/shares_value.py
mindsight_full_api/scripts/todo/alerts.py
mindsight_full_api/scripts/todo/plrs.py
mindsight_full_api/scripts/trainings.py
mindsight_full_api/scripts/users.py
mindsight_full_api/scripts/variable_salaries.py
mindsight_full_api/settings.py
mindsight_full_api/utils/__init__.py
mindsight_full_api/utils/aux_functions.py
mindsight_full_api-0.1.8.dist-info/METADATA
mindsight_full_api-0.1.8.dist-info/WHEEL
mindsight_full_api-0.1.8.dist-info/licenses/LICENSE
mindsight_full_api-0.1.8.dist-info/RECORD
