Metadata-Version: 2.4
Name: mindsight-full-api
Version: 0.1.8
Summary: Mindsight Full API to create, update and delete records
License: MIT
License-File: LICENSE
Author: stone_people_analytics
Author-email: systems-techpeople@stone.com.br
Maintainer: diogo56
Maintainer-email: diogo.amorim2001@gmail.com
Requires-Python: >=3.9,<4.0
Classifier: License :: OSI Approved :: MIT License
Classifier: Programming Language :: Python :: 3
Classifier: Programming Language :: Python :: 3.9
Classifier: Programming Language :: Python :: 3.10
Classifier: Programming Language :: Python :: 3.11
Classifier: Programming Language :: Python :: 3.12
Classifier: Programming Language :: Python :: 3.13
Classifier: Programming Language :: Python :: 3.14
Requires-Dist: pytest (>=7.4.2,<8.0.0)
Requires-Dist: python-decouple (>=3.8,<4.0)
Requires-Dist: requests (>=2.31.0,<3.0.0)
Project-URL: Repository, https://github.com/people-analytics-tech/mindsight-full-api
